detach.py
setup.cfg
setup.py
detach.egg-info/PKG-INFO
detach.egg-info/SOURCES.txt
detach.egg-info/dependency_links.txt
detach.egg-info/top_level.txt