Metadata-Version: 1.1
Name: detach
Version: 1.0
Summary: Fork and detach the current processe.
Home-page: https://github.com/bluedragonx/detach
Author: Ryan Bourgeois
Author-email: bluedragonx@gmail.com
License: BSD-derived
Keywords: fork daemon detach
Platform: UNKNOWN
Classifier: Intended Audience :: Developers
Classifier: Programming Language :: Python
Classifier: Programming Language :: Python :: 2
Classifier: Programming Language :: Python :: 2.7
Classifier: License :: OSI Approved :: BSD License
